beaquery/__about__.py
beaquery/__init__.py
beaquery/beafixedassets.py
beaquery/beagdpbyind.py
beaquery/beahierarchy.json
beaquery/beaiip.py
beaquery/beaillustrated.py
beaquery/beainputoutput.py
beaquery/beaissta.py
beaquery/beaistrade.py
beaquery/beaita.py
beaquery/beamne.py
beaquery/beanipa.py
beaquery/beaniud.py
beaquery/beaqueryq.py
beaquery/bearegional.py
beaquery/beaugdpbyind.py
beaquery/bqtest.py
beaquery/ebquery.py
beaquery-0.0.26.dist-info/METADATA
beaquery-0.0.26.dist-info/WHEEL
beaquery-0.0.26.dist-info/entry_points.txt
beaquery-0.0.26.dist-info/licenses/LICENSE.txt
beaquery-0.0.26.dist-info/RECORD
