Metadata-Version: 2.4
Name: beaquery
Version: 0.0.26
Project-URL: Documentation, https://github.com/dfwcnj/beaquery#readme
Project-URL: Issues, https://github.com/dfwcnj/beaquery/issues
Project-URL: Source, https://github.com/dfwcnj/beaquery
Author-email: Don Caldwell <dfcnj@gmail.com>
License-Expression: MIT
License-File: LICENSE.txt
Classifier: Development Status :: 4 - Beta
Classifier: Programming Language :: Python
Classifier: Programming Language :: Python :: 3.8
Classifier: Programming Language :: Python :: 3.9
Classifier: Programming Language :: Python :: 3.10
Classifier: Programming Language :: Python :: 3.11
Classifier: Programming Language :: Python :: 3.12
Classifier: Programming Language :: Python :: Implementation :: CPython
Classifier: Programming Language :: Python :: Implementation :: PyPy
Requires-Python: >=3.8
